btsmarthub_devicelist/__init__.py
btsmarthub_devicelist-0.2.3.dist-info/LICENSE
btsmarthub_devicelist-0.2.3.dist-info/METADATA
btsmarthub_devicelist-0.2.3.dist-info/WHEEL
btsmarthub_devicelist-0.2.3.dist-info/top_level.txt
btsmarthub_devicelist-0.2.3.dist-info/RECORD
