Metadata-Version: 2.1
Name: btsmarthub_devicelist
Version: 0.2.3
Summary: Retrieve a list of devices from a bt smarthub or bt smarthub 2 on a local network
Home-page: https://github.com/jxwolstenholme/btsmarthub_devicelist
Author: Jamie Wolstenholme
Author-email: jxwolstenholme@gmail.com
License: MIT
License-File: LICENSE
